tornkts
