Metadata-Version: 1.1
Name: tornkts
Version: 0.7.5
Summary: Tuned Tornado classes for simpler creation of powerful APIs
Home-page: https://github.com/KTSStudio/tornkts
Author: KTS
Author-email: tornkts@ktsstudio.ru
License: MIT
Download-URL: https://github.com/KTSStudio/tornkts/tarball/v0.7.5
Keywords: tornkts setuptools development
Platform: UNKNOWN
Classifier: Development Status :: 3 - Alpha
Classifier: Intended Audience :: Developers
Classifier: Topic :: Software Development :: Build Tools
Classifier: License :: OSI Approved :: MIT License
Classifier: Programming Language :: Python :: 2.6
Classifier: Programming Language :: Python :: 2.7
Classifier: Programming Language :: Python :: 3.4
